[
  {
    "model": "system.GajiPokok",
    "pk": 1,
    "fields": 
      {
        "karyawan_id": 1,
        "gajipokok" : 1500000,
        "jumlahhari": 5,
        "jabatan" : 150000,
        "created_at": "2017-03-01 15:03+07"
      }    
  },
  {
    "model": "system.GajiPokok",
    "pk": 2,
    "fields": 
      {
        "karyawan_id": 2,
        "gajipokok" : 300000,
        "jumlahhari": 6,
        "jabatan" : 150000,
        "created_at": "2017-03-01 15:03+07"
      }    
  },
  {
    "model": "system.GajiPokok",
    "pk": 3,
    "fields": 
      {
        "karyawan_id": 3,
        "gajipokok" : 500000,
        "jumlahhari": 6,
        "jabatan" : 150000,
        "created_at": "2017-03-01 15:03+07"
      }    
  },
{
    "model": "system.GajiPokok",
    "pk": 4,
    "fields": 
      {
        "karyawan_id": 4,
        "gajipokok" : 500000,
        "jumlahhari": 5,
        "jabatan" : 150000,
        "created_at": "2017-03-01 15:03+07"
      }    
  },
  {
    "model": "system.GajiPokok",
    "pk": 5,
    "fields": 
      {
        "karyawan_id": 5,
        "gajipokok" : 150000,
        "jumlahhari": 5,
        "jabatan" : 150000,
        "created_at": "2017-03-01 15:03+07"
      }    
  },
  {
    "model": "system.GajiPokok",
    "pk": 6,
    "fields": 
      {
        "karyawan_id": 6,
        "gajipokok" : 150000,
        "jumlahhari": 5,
        "jabatan" : 150000,
        "created_at": "2017-03-01 15:03+07"
      }    
  },
  {
    "model": "system.GajiPokok",
    "pk": 7,
    "fields": 
      {
        "karyawan_id": 7,
        "gajipokok" : 500000,
        "jumlahhari": 5,
        "jabatan" : 150000,
        "created_at": "2017-03-01 15:03+07"
      }    
  },
  {
    "model": "system.GajiPokok",
    "pk": 8,
    "fields": 
      {
        "karyawan_id": 8,
        "gajipokok" : 100000,
        "jumlahhari": 5,
        "jabatan" : 150000,
        "created_at": "2017-03-01 15:03+07"
      }    
  },
  {
    "model": "system.GajiPokok",
    "pk": 9,
    "fields": 
      {
        "karyawan_id": 9,
        "gajipokok" : 7000000,
        "jumlahhari": 5,
        "jabatan" : 150000,
        "created_at": "2017-03-01 15:03+07"
      }    
  },
  {
    "model": "system.GajiPokok",
    "pk": 10,
    "fields": 
      {
        "karyawan_id": 10,
        "jumlahhari": 5,
        "gajipokok" : 1500000,
        "jabatan" : 150000,
        "created_at": "2017-03-01 15:03+07"
      }    
  },
  {
    "model": "system.GajiPokok",
    "pk": 11,
    "fields": 
      {
        "karyawan_id": 11,
        "jumlahhari": 5,
        "gajipokok" : 5000000,
        "jabatan" : 150000,
        "created_at": "2017-03-01 15:03+07"
      }    
  },
  {
    "model": "system.GajiPokok",
    "pk": 12,
    "fields": 
      {
        "karyawan_id": 12,
        "jumlahhari": 5,
        "gajipokok" : 2000000,
        "jabatan" : 150000,
        "created_at": "2017-03-01 15:03+07"
      }    
  },
  {
    "model": "system.GajiPokok",
    "pk": 13,
    "fields": 
      {
        "karyawan_id": 13,
        "gajipokok" : 150000,
        "jumlahhari": 5,
        "jabatan" : 150000,
        "created_at": "2017-03-01 15:03+07"
      }    
  },
  {
    "model": "system.GajiPokok",
    "pk": 14,
    "fields": 
      {
        "karyawan_id": 14,
        "gajipokok" : 1500000,
        "jumlahhari": 5,
        "jabatan" : 150000,
        "created_at": "2017-03-01 15:03+07"
      }    
  },
  {
    "model": "system.GajiPokok",
    "pk": 15,
    "fields": 
      {
        "karyawan_id": 15,
        "gajipokok" : 500000,
        "jumlahhari": 5,
        "jabatan" : 150000,
        "created_at": "2017-03-01 15:03+07"
      }    
  },
  {
    "model": "system.GajiPokok",
    "pk": 16,
    "fields": 
      {
        "karyawan_id": 16,
        "gajipokok" : 4000000,
        "jumlahhari": 5,
        "jabatan" : 150000,
        "created_at": "2017-03-01 15:03+07"
      }    
  },
  {
    "model": "system.GajiPokok",
    "pk": 17,
    "fields": 
      {
        "karyawan_id": 17,
        "gajipokok" : 450000,
        "jumlahhari": 5,
        "jabatan" : 150000,
        "created_at": "2017-03-01 15:03+07"
      }
  },
  {
    "model": "system.GajiPokok",
    "pk": 18,
    "fields": 
      {
        "karyawan_id": 18,
        "gajipokok" : 350000,
        "jumlahhari": 5,
        "jabatan" : 150000,
        "created_at": "2017-03-01 15:03+07"
      }    
  },
  {
    "model": "system.GajiPokok",
    "pk": 19,
    "fields": 
      {
        "karyawan_id": 19,
        "gajipokok" : 650000,
        "jumlahhari": 5,
        "jabatan" : 150000,
        "created_at": "2017-03-01 15:03+07"
      } 
  },
  {
    "model": "system.GajiPokok",
    "pk": 20,
    "fields": 
      {
        "karyawan_id": 20,
        "gajipokok" : 170000,
        "jumlahhari": 5,
        "jabatan" : 150000,
        "created_at": "2017-03-01 15:03+07"
      }
  }
]